DPAD/DPADModel.py
DPAD/RNNModel.py
DPAD/RegressionModel.py
DPAD/__init__.py
DPAD/example/__init__.py
DPAD/tests/test_DPADModel.py
DPAD/tests/test_RNNModel.py
DPAD/tools/GaussianSmoother.py
DPAD/tools/LinearMapping.py
DPAD/tools/SSM.py
DPAD/tools/__init__.py
DPAD/tools/abstract_classes.py
DPAD/tools/evaluation.py
DPAD/tools/file_tools.py
DPAD/tools/flexible.py
DPAD/tools/model_base_classes.py
DPAD/tools/parse_tools.py
DPAD/tools/plot.py
DPAD/tools/plot_model_params.py
DPAD/tools/sim_tools.py
DPAD/tools/tf_losses.py
DPAD/tools/tf_tools.py
DPAD/tools/tools.py
DPAD/tools/tests/test_LinearMapping.py
DPAD/tools/tests/test_parse_tools.py
DPAD/tools/tests/test_tf_losses.py
DPAD/tools/tests/test_tools.py
dpad-0.0.9.dist-info/licenses/LICENSE.md
dpad-0.0.9.dist-info/METADATA
dpad-0.0.9.dist-info/WHEEL
dpad-0.0.9.dist-info/top_level.txt
dpad-0.0.9.dist-info/RECORD
