Metadata-Version: 2.4
Name: DPAD
Version: 0.0.9
Summary: Python implementation for DPAD (dissociative and prioritized analysis of dynamics)
Author-email: Omid Sani <omidsani@gmail.com>
Project-URL: Homepage, https://github.com/ShanechiLab/DPAD
Project-URL: Issues, https://github.com/ShanechiLab/DPAD/issues
Classifier: Programming Language :: Python :: 3
Classifier: Operating System :: OS Independent
Requires-Python: >=3.11
License-File: LICENSE.md
Requires-Dist: tensorflow==2.15.1
Requires-Dist: numpy==1.26.4
Requires-Dist: PSID==1.2.5
Requires-Dist: coloredlogs==15.0.1
Requires-Dist: tqdm==4.66.4
Requires-Dist: xxhash==3.5.0
Dynamic: license-file
